BDFunction1D-0.1.2.dist-info/NOTICE.txt
BDFunction1D-0.1.2.dist-info/RECORD
BDFunction1D-0.1.2.dist-info/WHEEL
BDFunction1D-0.1.2.dist-info/METADATA
BDFunction1D-0.1.2.dist-info/LICENSE.txt
BDFunction1D-0.1.2.dist-info/top_level.txt
BDFunction1D/Function.cpython-37m-x86_64-linux-gnu.so
BDFunction1D/Standard.pxd
BDFunction1D/Standard.cpython-37m-x86_64-linux-gnu.so
BDFunction1D/Functional.cpython-37m-x86_64-linux-gnu.so
BDFunction1D/Function.pxd
BDFunction1D/_helpers.pxd
BDFunction1D/BinaryFunctional.cpython-37m-x86_64-linux-gnu.so
BDFunction1D/__init__.py
BDFunction1D/BinaryFunctional.pxd
BDFunction1D/Differentiation.cpython-37m-x86_64-linux-gnu.so
BDFunction1D/Functional.pxd
BDFunction1D/_helpers.cpython-37m-x86_64-linux-gnu.so
BDFunction1D/Differentiation.pxd
BDFunction1D/_version.py
BDFunction1D/__init__.pxd
BDFunction1D/Interpolation.cpython-37m-x86_64-linux-gnu.so
BDFunction1D/Interpolation.pxd
