Metadata-Version: 2.1
Name: BDFunction1D
Version: 0.1.2
Summary: BD one dimensional real argument real value functions
Home-page: https://github.com/bond-anton/BDFunction1D
Author: Anton Bondarenko
Author-email: bond.anton@gmail.com
License: Apache Software License
Keywords: 1D R->R functions
Platform: UNKNOWN
Classifier: Development Status :: 3 - Alpha
Classifier: Intended Audience :: Education
Classifier: Intended Audience :: Science/Research
Classifier: License :: OSI Approved :: Apache Software License
Classifier: Topic :: Scientific/Engineering :: Mathematics
Classifier: Programming Language :: Python :: 3
Classifier: Programming Language :: Python :: 3.6
Classifier: Programming Language :: Python :: 3.7
Classifier: Programming Language :: Python :: 3.8
Classifier: Programming Language :: Python :: 3.9
